torch_exid/__init__.py
torch_exid/exid.py
torch_exid-0.1.5.dist-info/LICENSE
torch_exid-0.1.5.dist-info/WHEEL
torch_exid-0.1.5.dist-info/METADATA
torch_exid-0.1.5.dist-info/RECORD
