Metadata-Version: 2.1
Name: torch-exid
Version: 0.1.5
Summary: An extension of PyTorch IterableDataset, this package introduces functionalities for shuffling, limiting, and offsetting data.
Home-page: https://github.com/arlegotin/torch_exid
Author: Artem Legotin
Author-email: hello@artemlegotin.com
Requires-Python: >=3.8,<4.0
Classifier: Programming Language :: Python :: 3
Classifier: Programming Language :: Python :: 3.10
Classifier: Programming Language :: Python :: 3.8
Classifier: Programming Language :: Python :: 3.9
Requires-Dist: torch (>=2.0.1,<3.0.0)
